raking/__init__.py
raking/compute_constraints.py
raking/compute_covariance.py
raking/formatting_methods.py
raking/raking_methods.py
raking/run_raking.py
raking/uncertainty_methods.py
raking/experimental/__init__.py
raking/experimental/data.py
raking/experimental/dimension.py
raking/experimental/distance.py
raking/experimental/solver.py
raking-0.2.0.dist-info/licenses/LICENSE
raking-0.2.0.dist-info/METADATA
raking-0.2.0.dist-info/WHEEL
raking-0.2.0.dist-info/top_level.txt
raking-0.2.0.dist-info/RECORD
